nextbillionai/__init__.py
nextbillionai/_base_client.py
nextbillionai/_client.py
nextbillionai/_compat.py
nextbillionai/_constants.py
nextbillionai/_exceptions.py
nextbillionai/_files.py
nextbillionai/_models.py
nextbillionai/_qs.py
nextbillionai/_resource.py
nextbillionai/_response.py
nextbillionai/_streaming.py
nextbillionai/_types.py
nextbillionai/_version.py
nextbillionai/py.typed
nextbillionai/_utils/__init__.py
nextbillionai/_utils/_logs.py
nextbillionai/_utils/_proxy.py
nextbillionai/_utils/_reflection.py
nextbillionai/_utils/_resources_proxy.py
nextbillionai/_utils/_streams.py
nextbillionai/_utils/_sync.py
nextbillionai/_utils/_transform.py
nextbillionai/_utils/_typing.py
nextbillionai/_utils/_utils.py
nextbillionai/lib/.keep
nextbillionai/resources/__init__.py
nextbillionai/resources/areas.py
nextbillionai/resources/autocomplete.py
nextbillionai/resources/autosuggest.py
nextbillionai/resources/batch.py
nextbillionai/resources/browse.py
nextbillionai/resources/directions.py
nextbillionai/resources/discover.py
nextbillionai/resources/geocode.py
nextbillionai/resources/isochrone.py
nextbillionai/resources/lookup.py
nextbillionai/resources/map.py
nextbillionai/resources/mdm.py
nextbillionai/resources/navigation.py
nextbillionai/resources/postalcode.py
nextbillionai/resources/restrictions.py
nextbillionai/resources/restrictions_items.py
nextbillionai/resources/revgeocode.py
nextbillionai/resources/route_report.py
nextbillionai/resources/snap_to_roads.py
nextbillionai/resources/distance_matrix/__init__.py
nextbillionai/resources/distance_matrix/distance_matrix.py
nextbillionai/resources/distance_matrix/json.py
nextbillionai/resources/fleetify/__init__.py
nextbillionai/resources/fleetify/document_templates.py
nextbillionai/resources/fleetify/fleetify.py
nextbillionai/resources/fleetify/routes/__init__.py
nextbillionai/resources/fleetify/routes/routes.py
nextbillionai/resources/fleetify/routes/steps.py
nextbillionai/resources/geofence/__init__.py
nextbillion_sdk-0.4.0.dist-info/METADATA
nextbillion_sdk-0.4.0.dist-info/WHEEL
nextbillion_sdk-0.4.0.dist-info/licenses/LICENSE
nextbillion_sdk-0.4.0.dist-info/RECORD
